<?xml version="1.0"?>
<database xmlns:xsi="http://www.w3.org/2001/XMLSchema-instance" name="zed" xsi:noNamespaceSchemaLocation="http://static.spryker.com/schema-01.xsd" namespace="Orm\Zed\CustomerNote\Persistence" package="src.Orm.Zed.CustomerNote.Persistence">
  <table name="spy_customer_note">
    <index name="index-spy_customer_note-fk_customer">
      <index-column name="fk_customer"/>
    </index>
    <index name="index-spy_customer_note-fk_user">
      <index-column name="fk_user"/>
    </index>
  </table>
</database>
