<?xml version="1.0"?>
<database xmlns:xsi="http://www.w3.org/2001/XMLSchema-instance"
          name="zed"
          xsi:noNamespaceSchemaLocation="http://static.spryker.com/schema-01.xsd"
          namespace="Orm\Zed\QuoteRequest\Persistence" package="src.Orm.Zed.QuoteRequest.Persistence"
>
    <table name="spy_quote_request">
        <column name="id_quote_request" required="true" type="INTEGER" autoIncrement="true" primaryKey="true"/>
        <column name="fk_company_user" type="INTEGER" required="true"/>
        <column name="quote_request_reference" type="VARCHAR" size="255" required="true"/>
        <column name="valid_until" type="TIMESTAMP" required="false"/>
        <column name="status" type="VARCHAR" size="255"/>
        <column name="is_latest_version_visible" type="BOOLEAN" default="true"/>
        <column name="uuid" required="false" type="VARCHAR" size="255"/>

        <index name="spy_quote_request-fk_company_user">
            <index-column name="fk_company_user"/>
        </index>

        <index name="spy_quote_request-quote_request_reference">
            <index-column name="quote_request_reference"/>
        </index>

        <index name="spy_quote_request-status">
            <index-column name="status"/>
        </index>

        <index name="spy_quote_request-valid_until-status">
            <index-column name="valid_until"/>
            <index-column name="status"/>
        </index>

        <unique name="spy_quote_request-uuid">
            <unique-column name="uuid"/>
        </unique>
        <behavior name="uuid">
            <parameter name="key_columns" value="quote_request_reference"/>
        </behavior>

        <unique name="spy_quote_request-reference">
            <unique-column name="quote_request_reference"/>
        </unique>

        <foreign-key name="spy_quote_request-fk_company_user" foreignTable="spy_company_user" phpName="CompanyUser">
            <reference local="fk_company_user" foreign="id_company_user"/>
        </foreign-key>

        <behavior name="timestampable"/>

        <id-method-parameter value="spy_quote_request_pk_seq"/>
    </table>

    <table name="spy_quote_request_version">
        <column name="id_quote_request_version" required="true" type="INTEGER" autoIncrement="true" primaryKey="true"/>
        <column name="fk_quote_request" type="INTEGER" required="true"/>
        <column name="version" type="INTEGER" required="true"/>
        <column name="version_reference" type="VARCHAR" size="255"/>
        <column name="metadata" type="LONGVARCHAR" required="false"/>
        <column name="quote" type="LONGVARCHAR"/>

        <index name="spy_quote_request_version-fk_quote_request">
            <index-column name="fk_quote_request"/>
        </index>

        <index name="spy_quote_request_version-version">
            <index-column name="version"/>
        </index>

        <index name="spy_quote_request_version-version_reference">
            <index-column name="version_reference"/>
        </index>

        <foreign-key name="spy_quote_request_version-fk_quote_request" foreignTable="spy_quote_request">
            <reference foreign="id_quote_request" local="fk_quote_request"/>
        </foreign-key>

        <unique name="spy_quote_request_version-fk_quote_request-version">
            <unique-column name="fk_quote_request"/>
            <unique-column name="version"/>
        </unique>

        <behavior name="timestampable"/>

        <id-method-parameter value="spy_quote_request_version_pk_seq"/>
    </table>

</database>
